{"is_source_file": true, "description": "Simple md file", "external_files": [], "external_methods": [], "published": [], "calls": [], "search-terms": [], "classes": [], "methods": [], "state": 2, "file_id": 26, "knowledge_revision": 39, "git_revision": "1a533dadc095ff95c17ae1d95f158216d7f90a2c", "filename": "README.md", "hash": "6ec059727ee6b61597ed2d912a6ae78c", "format-version": 4, "code-base-name": "https://github.com/kavia-common/device-management-portal-23195-23204.git:kavia-main", "revision_history": [{"39": "1a533dadc095ff95c17ae1d95f158216d7f90a2c"}]}